{
  "type": "GROUP",
"name": "All Requests",
"path": "",
"pathFormatted": "group_missing-name--1146707516",
"stats": {
    "name": "All Requests",
    "numberOfRequests": {
        "total": 30,
        "ok": 30,
        "ko": 0
    },
    "minResponseTime": {
        "total": 12,
        "ok": 12,
        "ko": 0
    },
    "maxResponseTime": {
        "total": 42,
        "ok": 42,
        "ko": 0
    },
    "meanResponseTime": {
        "total": 31,
        "ok": 31,
        "ko": 0
    },
    "standardDeviation": {
        "total": 8,
        "ok": 8,
        "ko": 0
    },
    "percentiles1": {
        "total": 34,
        "ok": 34,
        "ko": 0
    },
    "percentiles2": {
        "total": 38,
        "ok": 38,
        "ko": 0
    },
    "percentiles3": {
        "total": 39,
        "ok": 39,
        "ko": 0
    },
    "percentiles4": {
        "total": 41,
        "ok": 41,
        "ko": 0
    },
    "group1": {
    "name": "t < 800 ms",
    "htmlName": "t < 800 ms",
    "count": 30,
    "percentage": 100
},
    "group2": {
    "name": "800 ms <= t < 1200 ms",
    "htmlName": "t >= 800 ms <br> t < 1200 ms",
    "count": 0,
    "percentage": 0
},
    "group3": {
    "name": "t >= 1200 ms",
    "htmlName": "t >= 1200 ms",
    "count": 0,
    "percentage": 0
},
    "group4": {
    "name": "failed",
    "htmlName": "failed",
    "count": 0,
    "percentage": 0
},
    "meanNumberOfRequestsPerSecond": {
        "total": 30.0,
        "ok": 30.0,
        "ko": 0
    }
},
"contents": {
"req_get-102230": {
        "type": "REQUEST",
        "name": "get",
"path": "get",
"pathFormatted": "req_get-102230",
"stats": {
    "name": "get",
    "numberOfRequests": {
        "total": 15,
        "ok": 15,
        "ko": 0
    },
    "minResponseTime": {
        "total": 29,
        "ok": 29,
        "ko": 0
    },
    "maxResponseTime": {
        "total": 42,
        "ok": 42,
        "ko": 0
    },
    "meanResponseTime": {
        "total": 36,
        "ok": 36,
        "ko": 0
    },
    "standardDeviation": {
        "total": 3,
        "ok": 3,
        "ko": 0
    },
    "percentiles1": {
        "total": 37,
        "ok": 37,
        "ko": 0
    },
    "percentiles2": {
        "total": 38,
        "ok": 38,
        "ko": 0
    },
    "percentiles3": {
        "total": 40,
        "ok": 40,
        "ko": 0
    },
    "percentiles4": {
        "total": 42,
        "ok": 42,
        "ko": 0
    },
    "group1": {
    "name": "t < 800 ms",
    "htmlName": "t < 800 ms",
    "count": 15,
    "percentage": 100
},
    "group2": {
    "name": "800 ms <= t < 1200 ms",
    "htmlName": "t >= 800 ms <br> t < 1200 ms",
    "count": 0,
    "percentage": 0
},
    "group3": {
    "name": "t >= 1200 ms",
    "htmlName": "t >= 1200 ms",
    "count": 0,
    "percentage": 0
},
    "group4": {
    "name": "failed",
    "htmlName": "failed",
    "count": 0,
    "percentage": 0
},
    "meanNumberOfRequestsPerSecond": {
        "total": 15.0,
        "ok": 15.0,
        "ko": 0
    }
}
    },"req_get-redirect-1--533510121": {
        "type": "REQUEST",
        "name": "get Redirect 1",
"path": "get Redirect 1",
"pathFormatted": "req_get-redirect-1--533510121",
"stats": {
    "name": "get Redirect 1",
    "numberOfRequests": {
        "total": 15,
        "ok": 15,
        "ko": 0
    },
    "minResponseTime": {
        "total": 12,
        "ok": 12,
        "ko": 0
    },
    "maxResponseTime": {
        "total": 38,
        "ok": 38,
        "ko": 0
    },
    "meanResponseTime": {
        "total": 26,
        "ok": 26,
        "ko": 0
    },
    "standardDeviation": {
        "total": 7,
        "ok": 7,
        "ko": 0
    },
    "percentiles1": {
        "total": 24,
        "ok": 24,
        "ko": 0
    },
    "percentiles2": {
        "total": 29,
        "ok": 29,
        "ko": 0
    },
    "percentiles3": {
        "total": 38,
        "ok": 38,
        "ko": 0
    },
    "percentiles4": {
        "total": 38,
        "ok": 38,
        "ko": 0
    },
    "group1": {
    "name": "t < 800 ms",
    "htmlName": "t < 800 ms",
    "count": 15,
    "percentage": 100
},
    "group2": {
    "name": "800 ms <= t < 1200 ms",
    "htmlName": "t >= 800 ms <br> t < 1200 ms",
    "count": 0,
    "percentage": 0
},
    "group3": {
    "name": "t >= 1200 ms",
    "htmlName": "t >= 1200 ms",
    "count": 0,
    "percentage": 0
},
    "group4": {
    "name": "failed",
    "htmlName": "failed",
    "count": 0,
    "percentage": 0
},
    "meanNumberOfRequestsPerSecond": {
        "total": 15.0,
        "ok": 15.0,
        "ko": 0
    }
}
    }
}

}